Metadata-Version: 2.1
Name: addDemo
Version: 1.0.2
Summary: A Python package upload test.
Home-page: UNKNOWN
Author: Koppula Praveen Kumar
Author-email: koppulapraveen920@gmail.com
License: MIT
Platform: UNKNOWN
Classifier: License :: OSI Approved :: MIT License
Classifier: Programming Language :: Python :: 3
Classifier: Programming Language :: Python :: 3.7
License-File: LICENSE
